material_ai/__init__.py
material_ai/api.py
material_ai/app.py
material_ai/auth.py
material_ai/config.py
material_ai/exec.py
material_ai/log_config.py
material_ai/request.py
material_ai/response.py
material_ai/theme.py
material_ai/ui_config.py
material_ai/agents/greeting_agent/__init__.py
material_ai/agents/greeting_agent/agent.py
material_ai/agents/material_ai_agent/__init__.py
material_ai/agents/material_ai_agent/agent.py
material_ai/handler/__init__.py
material_ai/handler/http_exception_handler.py
material_ai/middleware/__init__.py
material_ai/middleware/app_header_middleware.py
material_ai/middleware/auth_middleware.py
material_ai/oauth/__init__.py
material_ai/oauth/context.py
material_ai/oauth/google_oauth.py
material_ai/oauth/interface.py
material_ai/oauth/oauth.py
material_ai/oauth/schema.py
material_ai/oauth/util.py
material_ai/ui/dist/csv.png
material_ai/ui/dist/gemini.svg
material_ai/ui/dist/icon.svg
material_ai/ui/dist/index.html
material_ai/ui/dist/pdf.png
material_ai/ui/dist/vite.svg
material_ai/ui/dist/assets/Accordion-CuCFkhdM.js
material_ai/ui/dist/assets/AccordionActions-BKsumNk7.js
material_ai/ui/dist/assets/AccordionContext-7BkJYS_u.js
material_ai/ui/dist/assets/AccordionDetails-CQ2pcTbV.js
material_ai/ui/dist/assets/AccordionSummary-i5Djkdtb.js
material_ai/ui/dist/assets/Alert-CUoAMUo8.js
material_ai/ui/dist/assets/AlertTitle-s3yRjhyo.js
material_ai/ui/dist/assets/AppBar-CKZCV1Fy.js
material_ai/ui/dist/assets/Autocomplete-D7MBn9ly.js
material_ai/ui/dist/assets/Avatar-9_Jgm--b.js
material_ai/ui/dist/assets/Avatar-DGRKCuGo.js
material_ai/ui/dist/assets/AvatarGroup-DsDOWbW2.js
material_ai/ui/dist/assets/Backdrop-DFBlHYsE.js
material_ai/ui/dist/assets/Badge-3uN0eHlF.js
material_ai/ui/dist/assets/BottomNavigation-BZsXQDIj.js
material_ai/ui/dist/assets/BottomNavigationAction-6w-L8Wmg.js
material_ai/ui/dist/assets/Box-nY4HUnyc.js
material_ai/ui/dist/assets/Breadcrumbs-DZje7s1f.js
material_ai/ui/dist/assets/Button-CpchAnku.js
material_ai-1.1.18.dist-info/licenses/LICENSE
material_ai-1.1.18.dist-info/METADATA
material_ai-1.1.18.dist-info/WHEEL
material_ai-1.1.18.dist-info/top_level.txt
material_ai-1.1.18.dist-info/RECORD
