Metadata-Version: 2.4
Name: material-ai
Version: 1.1.18
Summary: Material AI Agent with FastAPI server
License: MIT
Project-URL: Repository, https://github.com/muralimanoharv/material-ai/tree/v1.1.18
Requires-Python: >=3.13
License-File: LICENSE
Requires-Dist: deprecated==1.2.18
Requires-Dist: fastapi[all]>=0.116.1
Requires-Dist: google-adk==1.17.0
Requires-Dist: psutil>=7.1.0
Requires-Dist: python-json-logger>=3.3.0
Requires-Dist: pyyaml>=6.0.3
Provides-Extra: dev
Requires-Dist: black>=25.9.0; extra == "dev"
Requires-Dist: build>=1.3.0; extra == "dev"
Requires-Dist: debugpy>=1.8.15; extra == "dev"
Requires-Dist: pytest>=8.4.2; extra == "dev"
Requires-Dist: pytest-cov>=7.0.0; extra == "dev"
Requires-Dist: respx>=0.22.0; extra == "dev"
Requires-Dist: twine>=6.2.0; extra == "dev"
Dynamic: license-file
